{
  "totalBets": 379,
  "wins": 215,
  "losses": 162,
  "pushes": 2,
  "winRate": 57.03,
  "totalWinnings": 26390.25,
  "totalLossesAmount": 20940.0,
  "avgWin": 122.75,
  "avgLoss": -129.26,
  "avgProfitPerBet": 14.38,
  "medianProfit": 86.96,
  "largestWin": 345,
  "largestLoss": -250,
  "profitFactor": 1.26,
  "maxWinStreak": 9,
  "maxLossStreak": 7,
  "currentStreak": -2,
  "totalCapitalRisked": 48865.0,
  "unitsRisked": 488.65,
  "maxDrawdown": -2037.98,
  "maxDrawdownPercent": -5.04,
  "maxDrawdownPeak": "2025-12-18",
  "maxDrawdownTrough": "2025-11-14",
  "maxDrawdownPeakBalance": 46317.85,
  "maxDrawdownTroughBalance": 38421.95,
  "currentDrawdown": {
    "amount": -867.6,
    "percentage": -1.87,
    "daysSincePeak": 10,
    "peakBalance": 46317.85,
    "peakDate": "2025-12-18",
    "currentBalance": 45450.25
  },
  "sharpeRatio": 4.88,
  "sharpeRatioNote": "52-day sample",
  "closingLineValue": null,
  "closingLineValueNote": "CLV tracking started Nov 27, 2025",
  "clvBetsTracked": 0,
  "clvTrackingStartDate": "2025-11-27",
  "rollingPerformance": {
    "last3Days": {
      "wins": 11,
      "losses": 14,
      "pnl": -52.55,
      "roi": -2.0,
      "bets": 25
    },
    "last7Days": {
      "wins": 23,
      "losses": 25,
      "pnl": -67.57,
      "roi": -1.27,
      "bets": 48
    },
    "last30Days": {
      "wins": 144,
      "losses": 106,
      "pnl": 4018.98,
      "roi": 13.01,
      "bets": 251
    }
  },
  "edgeValidation": {
    "lowEdge": {
      "wins": 61,
      "losses": 36,
      "pnl": 2637.5,
      "roi": 27.05,
      "bets": 98
    },
    "midEdge": {
      "wins": 65,
      "losses": 48,
      "pnl": 2099.24,
      "roi": 14.78,
      "bets": 113
    },
    "highEdge": {
      "wins": 89,
      "losses": 78,
      "pnl": 713.51,
      "roi": 2.86,
      "bets": 168
    },
    "isCorrelated": false
  },
  "evAnalysis": {
    "totalExpectedValue": 4444.5,
    "actualPL": 5450.25,
    "variance": 1005.75,
    "status": "Running Hot"
  },
  "sportBreakdown": {
    "NHL": {
      "record": {
        "wins": 39,
        "losses": 31
      },
      "pnl": 1123.81,
      "roi": 13.87,
      "totalBets": 71
    },
    "NCAAB": {
      "record": {
        "wins": 46,
        "losses": 30
      },
      "pnl": 1183.24,
      "roi": 12.29,
      "totalBets": 76
    },
    "NFL": {
      "record": {
        "wins": 39,
        "losses": 35
      },
      "pnl": 831.64,
      "roi": 8.62,
      "totalBets": 75
    },
    "Soccer": {
      "record": {
        "wins": 0,
        "losses": 1
      },
      "pnl": -150,
      "roi": -100.0,
      "totalBets": 1
    },
    "NBA": {
      "record": {
        "wins": 75,
        "losses": 48
      },
      "pnl": 2478.59,
      "roi": 14.7,
      "totalBets": 123
    },
    "NCAAF": {
      "record": {
        "wins": 16,
        "losses": 17
      },
      "pnl": -17.04,
      "roi": -0.38,
      "totalBets": 33
    }
  },
  "betTypeBreakdown": {
    "Moneyline": {
      "record": {
        "wins": 32,
        "losses": 27
      },
      "pnl": 984.26,
      "roi": 14.58,
      "winRate": 54.24,
      "totalBets": 59
    },
    "Props": {
      "record": {
        "wins": 22,
        "losses": 26
      },
      "pnl": -1178.8,
      "roi": -17.93,
      "winRate": 45.83,
      "totalBets": 48
    },
    "Spread": {
      "record": {
        "wins": 147,
        "losses": 87
      },
      "pnl": 6824.23,
      "roi": 22.07,
      "winRate": 62.82,
      "totalBets": 235
    },
    "Total": {
      "record": {
        "wins": 14,
        "losses": 22
      },
      "pnl": -1179.44,
      "roi": -25.5,
      "winRate": 38.89,
      "totalBets": 37
    }
  },
  "stakeBreakdown": {
    "highConviction": {
      "label": "High Conviction",
      "range": "1.5u+",
      "record": {
        "wins": 100,
        "losses": 72
      },
      "pnl": 3547.88,
      "roi": 11.91,
      "winRate": 58.14
    },
    "standard": {
      "label": "Standard",
      "range": "1.0u",
      "record": {
        "wins": 91,
        "losses": 69
      },
      "pnl": 1827.03,
      "roi": 11.11,
      "winRate": 56.88
    },
    "lowConviction": {
      "label": "Low Conviction",
      "range": "0.5-0.75u",
      "record": {
        "wins": 24,
        "losses": 21
      },
      "pnl": 75.34,
      "roi": 2.87,
      "winRate": 53.33
    }
  },
  "fundMetrics": {
    "SharpFund": {
      "wins": 83,
      "losses": 50,
      "pnl": 3631.72,
      "roi": 22.14,
      "winRate": 62.41,
      "totalBets": 133
    },
    "CatalystFund": {
      "wins": 20,
      "losses": 14,
      "pnl": 968.18,
      "roi": 26.17,
      "winRate": 58.82,
      "totalBets": 35
    },
    "VectorFund": {
      "wins": 95,
      "losses": 87,
      "pnl": 31.63,
      "roi": 0.12,
      "winRate": 52.2,
      "totalBets": 183
    },
    "ContraFund": {
      "wins": 17,
      "losses": 11,
      "pnl": 818.72,
      "roi": 24.08,
      "winRate": 60.71,
      "totalBets": 28
    }
  },
  "portfolioGrowth": [
    {
      "date": "2025-11-04",
      "balance": 40100,
      "profit": 100,
      "description": "Maxey O3.5 3-pointers",
      "result": "win"
    },
    {
      "date": "2025-11-04",
      "balance": 40160.61,
      "profit": 60.61,
      "description": "Murphy III O2.5 3-pointers",
      "result": "win"
    },
    {
      "date": "2025-11-04",
      "balance": 40243.94,
      "profit": 83.33,
      "description": "Booker O28.5 points",
      "result": "win"
    },
    {
      "date": "2025-11-05",
      "balance": 40143.94,
      "profit": -100,
      "description": "Wembanyama O12.5 rebounds",
      "result": "loss"
    },
    {
      "date": "2025-11-05",
      "balance": 40271.06,
      "profit": 127.12,
      "description": "Randle O20.5 points",
      "result": "win"
    },
    {
      "date": "2025-11-06",
      "balance": 40071.06,
      "profit": -200,
      "description": "Drake/Robert Morris U150.5",
      "result": "loss"
    },
    {
      "date": "2025-11-06",
      "balance": 40213.92,
      "profit": 142.86,
      "description": "Jackson State +38.5",
      "result": "win"
    },
    {
      "date": "2025-11-06",
      "balance": 40063.92,
      "profit": -150,
      "description": "Illinois State +1.5",
      "result": "loss"
    },
    {
      "date": "2025-11-06",
      "balance": 39913.92,
      "profit": -150,
      "description": "Bowers O64.5 receiving yards",
      "result": "loss"
    },
    {
      "date": "2025-11-06",
      "balance": 40063.92,
      "profit": 150,
      "description": "Dobbins O70.5 rushing yards",
      "result": "win"
    },
    {
      "date": "2025-11-06",
      "balance": 40154.83,
      "profit": 90.91,
      "description": "Smith U10.5 rushing yards",
      "result": "win"
    },
    {
      "date": "2025-11-07",
      "balance": 40308.68,
      "profit": 153.85,
      "description": "Giddey O8.5 assists",
      "result": "win"
    },
    {
      "date": "2025-11-07",
      "balance": 40158.68,
      "profit": -150,
      "description": "Thompson U16.5 points",
      "result": "loss"
    },
    {
      "date": "2025-11-07",
      "balance": 40008.68,
      "profit": -150,
      "description": "Mitchell U26.5 points",
      "result": "loss"
    },
    {
      "date": "2025-11-07",
      "balance": 40173.68,
      "profit": 165,
      "description": "Banchero O8.5 rebounds",
      "result": "win"
    },
    {
      "date": "2025-11-07",
      "balance": 40023.68,
      "profit": -150,
      "description": "Joki\u0107 U12.5 rebounds",
      "result": "loss"
    },
    {
      "date": "2025-11-07",
      "balance": 40147.68,
      "profit": 124,
      "description": "Barrett O3.5 assists",
      "result": "win"
    },
    {
      "date": "2025-11-08",
      "balance": 40329.5,
      "profit": 181.82,
      "description": "Oregon @ Iowa U41.5",
      "result": "win"
    },
    {
      "date": "2025-11-08",
      "balance": 40459.93,
      "profit": 130.43,
      "description": "Texas A&M -6.5",
      "result": "win"
    },
    {
      "date": "2025-11-08",
      "balance": 40359.93,
      "profit": -100,
      "description": "TCU -7.5",
      "result": "loss"
    },
    {
      "date": "2025-11-09",
      "balance": 40259.93,
      "profit": -100,
      "description": "Gadsden O53.5 receiving yards",
      "result": "loss"
    },
    {
      "date": "2025-11-09",
      "balance": 40159.93,
      "profit": -100,
      "description": "Gainwell O2.5 receptions",
      "result": "loss"
    },
    {
      "date": "2025-11-09",
      "balance": 40290.36,
      "profit": 130.43,
      "description": "Allen U44.5 receiving yards",
      "result": "win"
    },
    {
      "date": "2025-11-09",
      "balance": 40240.36,
      "profit": -50,
      "description": "Cook O84.5 rushing yards",
      "result": "loss"
    },
    {
      "date": "2025-11-09",
      "balance": 40165.36,
      "profit": -75,
      "description": "Collins Anytime TD",
      "result": "loss"
    },
    {
      "date": "2025-11-09",
      "balance": 40065.36,
      "profit": -100,
      "description": "Judkins O81.5 rushing yards",
      "result": "loss"
    },
    {
      "date": "2025-11-09",
      "balance": 39965.36,
      "profit": -100,
      "description": "Jaguars @ Texans U37.5",
      "result": "loss"
    },
    {
      "date": "2025-11-09",
      "balance": 40067.36,
      "profit": 102,
      "description": "White O3.5 receptions",
      "result": "win"
    },
    {
      "date": "2025-11-09",
      "balance": 39917.36,
      "profit": -150,
      "description": "Smith-Njigba O96.5 receiving yards",
      "result": "loss"
    },
    {
      "date": "2025-11-09",
      "balance": 39717.36,
      "profit": -200,
      "description": "Dowdle O19.5 rush attempts",
      "result": "loss"
    },
    {
      "date": "2025-11-10",
      "balance": 39895.93,
      "profit": 178.57,
      "description": "Jacobs Anytime TD",
      "result": "win"
    },
    {
      "date": "2025-11-10",
      "balance": 39645.93,
      "profit": -250,
      "description": "Love O225.5 passing yards",
      "result": "loss"
    },
    {
      "date": "2025-11-10",
      "balance": 39812.6,
      "profit": 166.67,
      "description": "Eagles +1.5",
      "result": "win"
    },
    {
      "date": "2025-11-10",
      "balance": 39612.6,
      "profit": -200,
      "description": "Hurts Anytime TD",
      "result": "loss"
    },
    {
      "date": "2025-11-10",
      "balance": 39512.6,
      "profit": -100,
      "description": "Smith O4.5 receptions",
      "result": "loss"
    },
    {
      "date": "2025-11-11",
      "balance": 39676.53,
      "profit": 163.93,
      "description": "Brunson O6.5 assists",
      "result": "win"
    },
    {
      "date": "2025-11-11",
      "balance": 39426.53,
      "profit": -250,
      "description": "Maxey O37.5 PTS+AST",
      "result": "loss"
    },
    {
      "date": "2025-11-11",
      "balance": 39513.49,
      "profit": 86.96,
      "description": "Jokic O26.5 points",
      "result": "win"
    },
    {
      "date": "2025-11-11",
      "balance": 39363.49,
      "profit": -150,
      "description": "Texas Tech +3.5",
      "result": "loss"
    },
    {
      "date": "2025-11-11",
      "balance": 39263.49,
      "profit": -100,
      "description": "Mitchell O23.5 PRA",
      "result": "loss"
    },
    {
      "date": "2025-11-11",
      "balance": 39163.49,
      "profit": -100,
      "description": "White U3.5 three-pointers",
      "result": "loss"
    },
    {
      "date": "2025-11-12",
      "balance": 38963.49,
      "profit": -200,
      "description": "Spurs -3.5",
      "result": "loss"
    },
    {
      "date": "2025-11-12",
      "balance": 38813.49,
      "profit": -150,
      "description": "Lakers +8.5",
      "result": "loss"
    },
    {
      "date": "2025-11-12",
      "balance": 38907.83,
      "profit": 94.34,
      "description": "Wembanyama O26.5 points",
      "result": "win"
    },
    {
      "date": "2025-11-12",
      "balance": 38807.83,
      "profit": -100,
      "description": "Sengun O22.5 points",
      "result": "loss"
    },
    {
      "date": "2025-11-13",
      "balance": 39031.04,
      "profit": 223.21428571428572,
      "description": "Jets vs Patriots UNDER 43.5",
      "result": "win"
    },
    {
      "date": "2025-11-13",
      "balance": 38831.04,
      "profit": -200,
      "description": "TreVeyon Henderson OVER 70.5 Rushing Yards",
      "result": "loss"
    },
    {
      "date": "2025-11-13",
      "balance": 38681.04,
      "profit": -150,
      "description": "Drake Maye OVER 1.5 Passing TDs",
      "result": "loss"
    },
    {
      "date": "2025-11-13",
      "balance": 38771.95,
      "profit": 90.9090909090909,
      "description": "Breece Hall UNDER 58.5 Rushing Yards",
      "result": "win"
    },
    {
      "date": "2025-11-13",
      "balance": 38721.95,
      "profit": -50,
      "description": "Jets +12.5",
      "result": "loss"
    },
    {
      "date": "2025-11-14",
      "balance": 38621.95,
      "profit": -100,
      "description": "76ers +2",
      "result": "loss"
    },
    {
      "date": "2025-11-14",
      "balance": 38421.95,
      "profit": -200,
      "description": "Mavericks +3.5",
      "result": "loss"
    },
    {
      "date": "2025-11-14",
      "balance": 38612.43,
      "profit": 190.47619047619048,
      "description": "Arizona -1.5",
      "result": "win"
    },
    {
      "date": "2025-11-15",
      "balance": 38802.91,
      "profit": 190.48,
      "description": "Iowa +6.5",
      "result": "win"
    },
    {
      "date": "2025-11-15",
      "balance": 38602.91,
      "profit": -200,
      "description": "Texas +4.5",
      "result": "loss"
    },
    {
      "date": "2025-11-15",
      "balance": 38793.39,
      "profit": 190.48,
      "description": "Oklahoma +6.5",
      "result": "win"
    },
    {
      "date": "2025-11-16",
      "balance": 38975.21,
      "profit": 181.82,
      "description": "Barkley O70.5 rushing yards",
      "result": "win"
    },
    {
      "date": "2025-11-16",
      "balance": 38775.21,
      "profit": -200,
      "description": "St. Brown O7.5 receptions",
      "result": "loss"
    },
    {
      "date": "2025-11-16",
      "balance": 38870.45,
      "profit": 95.24,
      "description": "Hurts O30.5 rushing yards",
      "result": "win"
    },
    {
      "date": "2025-11-17",
      "balance": 39099.81,
      "profit": 229.36,
      "description": "Pistons -11",
      "result": "win"
    },
    {
      "date": "2025-11-17",
      "balance": 39246.87,
      "profit": 147.06,
      "description": "Timberwolves -14.5",
      "result": "win"
    },
    {
      "date": "2025-11-17",
      "balance": 39106.87,
      "profit": -140,
      "description": "Pacers +10.5",
      "result": "loss"
    },
    {
      "date": "2025-11-17",
      "balance": 39006.87,
      "profit": -100,
      "description": "Gonzaga/Southern Utah Under 160.5",
      "result": "loss"
    },
    {
      "date": "2025-11-18",
      "balance": 38756.87,
      "profit": -250,
      "description": "Hawks +1.5",
      "result": "loss"
    },
    {
      "date": "2025-11-18",
      "balance": 38847.78,
      "profit": 90.91,
      "description": "Magic +3.5",
      "result": "win"
    },
    {
      "date": "2025-11-18",
      "balance": 38938.69,
      "profit": 90.91,
      "description": "Duke -10.5",
      "result": "win"
    },
    {
      "date": "2025-11-18",
      "balance": 39129.17,
      "profit": 190.48,
      "description": "Suns +2.5",
      "result": "win"
    },
    {
      "date": "2025-11-18",
      "balance": 39191.17,
      "profit": 62,
      "description": "Suns ML",
      "result": "win"
    },
    {
      "date": "2025-11-19",
      "balance": 39234.65,
      "profit": 43.48,
      "description": "Capitals ML",
      "result": "win"
    },
    {
      "date": "2025-11-19",
      "balance": 39354.65,
      "profit": 120,
      "description": "Raptors ML",
      "result": "win"
    },
    {
      "date": "2025-11-19",
      "balance": 39447.24,
      "profit": 92.59,
      "description": "Arizona +6.5",
      "result": "win"
    },
    {
      "date": "2025-11-19",
      "balance": 39583.6,
      "profit": 136.36,
      "description": "Heat -10",
      "result": "win"
    },
    {
      "date": "2025-11-20",
      "balance": 39627.46,
      "profit": 43.86,
      "description": "Cook O73.5 Rush Yds",
      "result": "win"
    },
    {
      "date": "2025-11-20",
      "balance": 39527.46,
      "profit": -100,
      "description": "Hawks +1.5",
      "result": "loss"
    },
    {
      "date": "2025-11-20",
      "balance": 39588.07,
      "profit": 60.61,
      "description": "Lightning ML",
      "result": "win"
    },
    {
      "date": "2025-11-20",
      "balance": 39724.43,
      "profit": 136.36,
      "description": "Under 44.5",
      "result": "win"
    },
    {
      "date": "2025-11-20",
      "balance": 39924.43,
      "profit": 200,
      "description": "Texans +5.5",
      "result": "win"
    },
    {
      "date": "2025-11-21",
      "balance": 40060.79,
      "profit": 136.36,
      "description": "Mitchell O28.5 pts",
      "result": "win"
    },
    {
      "date": "2025-11-21",
      "balance": 39910.79,
      "profit": -150,
      "description": "Castellanos O235.5 pass yds",
      "result": "loss"
    },
    {
      "date": "2025-11-21",
      "balance": 39982.22,
      "profit": 71.43,
      "description": "Hurricanes ML",
      "result": "win"
    },
    {
      "date": "2025-11-21",
      "balance": 39882.22,
      "profit": -100,
      "description": "Timberwolves -4.5",
      "result": "loss"
    },
    {
      "date": "2025-11-21",
      "balance": 39782.22,
      "profit": -100,
      "description": "Nuggets/Rockets O235.5",
      "result": "loss"
    },
    {
      "date": "2025-11-22",
      "balance": 39632.22,
      "profit": -150,
      "description": "Army -10",
      "result": "loss"
    },
    {
      "date": "2025-11-22",
      "balance": 39482.22,
      "profit": -150,
      "description": "Haaland Anytime Goal",
      "result": "loss"
    },
    {
      "date": "2025-11-22",
      "balance": 39332.22,
      "profit": -150,
      "description": "Daniels O2.5 stl",
      "result": "loss"
    },
    {
      "date": "2025-11-22",
      "balance": 39182.22,
      "profit": -150,
      "description": "Towns O11.5 Rebs",
      "result": "loss"
    },
    {
      "date": "2025-11-22",
      "balance": 39132.22,
      "profit": -50,
      "description": "Illinois -8.5",
      "result": "loss"
    },
    {
      "date": "2025-11-22",
      "balance": 39269.83,
      "profit": 137.61,
      "description": "Pistons -8",
      "result": "win"
    },
    {
      "date": "2025-11-23",
      "balance": 39312.2,
      "profit": 42.37,
      "description": "Heat ML",
      "result": "win"
    },
    {
      "date": "2025-11-23",
      "balance": 39399.16,
      "profit": 86.96,
      "description": "Maye O255.5 pass yds",
      "result": "win"
    },
    {
      "date": "2025-11-23",
      "balance": 39299.16,
      "profit": -100,
      "description": "Lions/Giants U50.5",
      "result": "loss"
    },
    {
      "date": "2025-11-23",
      "balance": 39299.16,
      "profit": 0,
      "description": "Bears -3",
      "result": "push"
    },
    {
      "date": "2025-11-23",
      "balance": 39199.16,
      "profit": -100,
      "description": "Patriots -7.5",
      "result": "loss"
    },
    {
      "date": "2025-11-23",
      "balance": 39099.16,
      "profit": -100,
      "description": "Eagles -3",
      "result": "loss"
    },
    {
      "date": "2025-11-24",
      "balance": 39246.22,
      "profit": 147.06,
      "description": "Gonzaga -4.5",
      "result": "win"
    },
    {
      "date": "2025-11-24",
      "balance": 39346.22,
      "profit": 100,
      "description": "McCaffrey O16.5 rush att",
      "result": "win"
    },
    {
      "date": "2025-11-24",
      "balance": 39476.65,
      "profit": 130.43,
      "description": "Nuggets -7.5",
      "result": "win"
    },
    {
      "date": "2025-11-24",
      "balance": 39567.56,
      "profit": 90.91,
      "description": "St. John's +2.5",
      "result": "win"
    },
    {
      "date": "2025-11-25",
      "balance": 39367.56,
      "profit": -200,
      "description": "Houston/Tennessee U135.5",
      "result": "loss"
    },
    {
      "date": "2025-11-25",
      "balance": 39465.6,
      "profit": 98.04,
      "description": "William & Mary -1.5",
      "result": "win"
    },
    {
      "date": "2025-11-25",
      "balance": 39265.6,
      "profit": -200,
      "description": "Hawks -10.5",
      "result": "loss"
    },
    {
      "date": "2025-11-25",
      "balance": 39383.6,
      "profit": 118,
      "description": "Stars ML",
      "result": "win"
    },
    {
      "date": "2025-11-26",
      "balance": 39470.56,
      "profit": 86.96,
      "description": "Fresno State -1.5",
      "result": "win"
    },
    {
      "date": "2025-11-26",
      "balance": 39558.28,
      "profit": 87.72,
      "description": "Fresno State -1.5",
      "result": "win"
    },
    {
      "date": "2025-11-26",
      "balance": 39748.76,
      "profit": 190.48,
      "description": "MIN +10.5",
      "result": "win"
    },
    {
      "date": "2025-11-26",
      "balance": 39939.24,
      "profit": 190.48,
      "description": "MIN +10.5",
      "result": "win"
    },
    {
      "date": "2025-11-26",
      "balance": 40064.24,
      "profit": 125,
      "description": "Houston Christian +1.5",
      "result": "win"
    },
    {
      "date": "2025-11-26",
      "balance": 40230.91,
      "profit": 166.67,
      "description": "Houston Christian +1.5",
      "result": "win"
    },
    {
      "date": "2025-11-26",
      "balance": 40130.91,
      "profit": -100,
      "description": "Florida Panthers ML",
      "result": "loss"
    },
    {
      "date": "2025-11-26",
      "balance": 39930.91,
      "profit": -200,
      "description": "New Orleans Pelicans +3.5",
      "result": "loss"
    },
    {
      "date": "2025-11-26",
      "balance": 40046.29,
      "profit": 115.38,
      "description": "Minnesota Wild ML",
      "result": "win"
    },
    {
      "date": "2025-11-26",
      "balance": 40166.29,
      "profit": 120,
      "description": "Dallas Stars ML",
      "result": "win"
    },
    {
      "date": "2025-11-27",
      "balance": 40213.91,
      "profit": 47.62,
      "description": "Packers +3",
      "result": "win"
    },
    {
      "date": "2025-11-27",
      "balance": 40413.91,
      "profit": 200,
      "description": "Illinois St -5.5",
      "result": "win"
    },
    {
      "date": "2025-11-27",
      "balance": 40263.91,
      "profit": -150,
      "description": "TCU/Florida Under 157",
      "result": "loss"
    },
    {
      "date": "2025-11-27",
      "balance": 40406.77,
      "profit": 142.86,
      "description": "Arkansas +11.5",
      "result": "win"
    },
    {
      "date": "2025-11-27",
      "balance": 40306.77,
      "profit": -100,
      "description": "Ravens -7",
      "result": "loss"
    },
    {
      "date": "2025-11-27",
      "balance": 40406.77,
      "profit": 100,
      "description": "Bengals +7",
      "result": "win"
    },
    {
      "date": "2025-11-27",
      "balance": 40556.77,
      "profit": 150,
      "description": "Cowboys +3",
      "result": "win"
    },
    {
      "date": "2025-11-27",
      "balance": 40706.77,
      "profit": 150,
      "description": "Cowboys +3",
      "result": "win"
    },
    {
      "date": "2025-11-27",
      "balance": 40856.77,
      "profit": 150,
      "description": "Cowboys +3",
      "result": "win"
    },
    {
      "date": "2025-11-27",
      "balance": 41056.77,
      "profit": 200,
      "description": "Cowboys +3",
      "result": "win"
    },
    {
      "date": "2025-11-27",
      "balance": 40956.77,
      "profit": -100,
      "description": "Cowboys/Chiefs Under 53",
      "result": "loss"
    },
    {
      "date": "2025-11-27",
      "balance": 40856.77,
      "profit": -100,
      "description": "Cowboys/Chiefs Under 53",
      "result": "loss"
    },
    {
      "date": "2025-11-27",
      "balance": 41003.83,
      "profit": 147.06,
      "description": "Michigan St -1.5",
      "result": "win"
    },
    {
      "date": "2025-11-27",
      "balance": 41090.79,
      "profit": 86.96,
      "description": "Stanford -2",
      "result": "win"
    },
    {
      "date": "2025-11-27",
      "balance": 41240.79,
      "profit": 150,
      "description": "Cowboys +3",
      "result": "win"
    },
    {
      "date": "2025-11-27",
      "balance": 41431.27,
      "profit": 190.48,
      "description": "Wisconsin -6.5",
      "result": "win"
    },
    {
      "date": "2025-11-28",
      "balance": 41574.13,
      "profit": 142.86,
      "description": "Avalanche/Wild Under 6",
      "result": "win"
    },
    {
      "date": "2025-11-28",
      "balance": 41374.13,
      "profit": -200,
      "description": "Golden Knights -1.5",
      "result": "loss"
    },
    {
      "date": "2025-11-28",
      "balance": 41694.13,
      "profit": 320,
      "description": "Capitals -1.5",
      "result": "win"
    },
    {
      "date": "2025-11-28",
      "balance": 41836.99,
      "profit": 142.86,
      "description": "TCU +6.5",
      "result": "win"
    },
    {
      "date": "2025-11-28",
      "balance": 41686.99,
      "profit": -150,
      "description": "Nets +7.5",
      "result": "loss"
    },
    {
      "date": "2025-11-29",
      "balance": 41872.18,
      "profit": 185.19,
      "description": "Troy +6.5",
      "result": "win"
    },
    {
      "date": "2025-11-29",
      "balance": 41672.18,
      "profit": -200,
      "description": "HCU +7.5",
      "result": "loss"
    },
    {
      "date": "2025-11-29",
      "balance": 41522.18,
      "profit": -150,
      "description": "Pitt +6.5",
      "result": "loss"
    },
    {
      "date": "2025-11-29",
      "balance": 41665.04,
      "profit": 142.86,
      "description": "BYU -17.5",
      "result": "win"
    },
    {
      "date": "2025-11-29",
      "balance": 41801.4,
      "profit": 136.36,
      "description": "ULM +10.5",
      "result": "win"
    },
    {
      "date": "2025-11-29",
      "balance": 41751.4,
      "profit": -50,
      "description": "FSU +1.5",
      "result": "loss"
    },
    {
      "date": "2025-11-29",
      "balance": 41929.97,
      "profit": 178.57,
      "description": "Pelicans +9",
      "result": "win"
    },
    {
      "date": "2025-11-29",
      "balance": 41879.97,
      "profit": -50,
      "description": "HCU +7.5",
      "result": "loss"
    },
    {
      "date": "2025-11-29",
      "balance": 41729.97,
      "profit": -150,
      "description": "Arkansas +4.5",
      "result": "loss"
    },
    {
      "date": "2025-11-29",
      "balance": 41872.83,
      "profit": 142.86,
      "description": "Hornets +9",
      "result": "win"
    },
    {
      "date": "2025-11-29",
      "balance": 41672.83,
      "profit": -200,
      "description": "Nets +11.5",
      "result": "loss"
    },
    {
      "date": "2025-11-29",
      "balance": 41896.04,
      "profit": 223.21,
      "description": "Pelicans +9",
      "result": "win"
    },
    {
      "date": "2025-11-30",
      "balance": 41746.04,
      "profit": -150,
      "description": "Colts -3",
      "result": "loss"
    },
    {
      "date": "2025-11-30",
      "balance": 41791.49,
      "profit": 45.45,
      "description": "SF/CLE Under 35.5",
      "result": "win"
    },
    {
      "date": "2025-11-30",
      "balance": 41884.08,
      "profit": 92.59,
      "description": "Jets +3",
      "result": "win"
    },
    {
      "date": "2025-11-30",
      "balance": 41684.08,
      "profit": -200,
      "description": "Jazz +11.5",
      "result": "loss"
    },
    {
      "date": "2025-11-30",
      "balance": 41738.08,
      "profit": 54,
      "description": "Blackhawks ML",
      "result": "win"
    },
    {
      "date": "2025-11-30",
      "balance": 41538.08,
      "profit": -200,
      "description": "Steelers +3",
      "result": "loss"
    },
    {
      "date": "2025-11-30",
      "balance": 41676.97,
      "profit": 138.89,
      "description": "Trail Blazers +11.5",
      "result": "win"
    },
    {
      "date": "2025-11-30",
      "balance": 41813.33,
      "profit": 136.36,
      "description": "Celtics +7",
      "result": "win"
    },
    {
      "date": "2025-12-01",
      "balance": 41904.24,
      "profit": 90.91,
      "description": "Hawks +9.5",
      "result": "win"
    },
    {
      "date": "2025-12-01",
      "balance": 41904.24,
      "profit": 0,
      "description": "Jets/Sabres Over 6",
      "result": "push"
    },
    {
      "date": "2025-12-01",
      "balance": 42041.85,
      "profit": 137.61,
      "description": "Nets +4.5",
      "result": "win"
    },
    {
      "date": "2025-12-01",
      "balance": 42132.76,
      "profit": 90.91,
      "description": "Bulls +9",
      "result": "win"
    },
    {
      "date": "2025-12-01",
      "balance": 42262.76,
      "profit": 130,
      "description": "Ducks ML",
      "result": "win"
    },
    {
      "date": "2025-12-01",
      "balance": 42394.34,
      "profit": 131.58,
      "description": "Jazz +12.5",
      "result": "win"
    },
    {
      "date": "2025-12-01",
      "balance": 42576.16,
      "profit": 181.82,
      "description": "Mavericks +11.5",
      "result": "win"
    },
    {
      "date": "2025-12-01",
      "balance": 42476.16,
      "profit": -100,
      "description": "Pacers +6.5",
      "result": "loss"
    },
    {
      "date": "2025-12-01",
      "balance": 42567.07,
      "profit": 90.91,
      "description": "Iona -1.5",
      "result": "win"
    },
    {
      "date": "2025-12-01",
      "balance": 42663.22,
      "profit": 96.15,
      "description": "North Alabama +5.5",
      "result": "win"
    },
    {
      "date": "2025-12-01",
      "balance": 42708.67,
      "profit": 45.45,
      "description": "Middle Tenn +2.5",
      "result": "win"
    },
    {
      "date": "2025-12-02",
      "balance": 42658.67,
      "profit": -50,
      "description": "Bruins ML",
      "result": "loss"
    },
    {
      "date": "2025-12-02",
      "balance": 42558.67,
      "profit": -100,
      "description": "Wizards +13.5",
      "result": "loss"
    },
    {
      "date": "2025-12-02",
      "balance": 42651.26,
      "profit": 92.59,
      "description": "Texas A&M -3.5",
      "result": "win"
    },
    {
      "date": "2025-12-02",
      "balance": 42710.08,
      "profit": 58.82,
      "description": "Maple Leafs +1.5",
      "result": "win"
    },
    {
      "date": "2025-12-02",
      "balance": 42846.44,
      "profit": 136.36,
      "description": "Celtics +1",
      "result": "win"
    },
    {
      "date": "2025-12-02",
      "balance": 43028.26,
      "profit": 181.82,
      "description": "Pelicans +12.5",
      "result": "win"
    },
    {
      "date": "2025-12-02",
      "balance": 43085.4,
      "profit": 57.14,
      "description": "Wild +1.5",
      "result": "win"
    },
    {
      "date": "2025-12-02",
      "balance": 42885.4,
      "profit": -200,
      "description": "Kansas +2.5",
      "result": "loss"
    },
    {
      "date": "2025-12-02",
      "balance": 42933.02,
      "profit": 47.62,
      "description": "UNC +6.5",
      "result": "win"
    },
    {
      "date": "2025-12-02",
      "balance": 43083.02,
      "profit": 150,
      "description": "Blackhawks +1.5",
      "result": "win"
    },
    {
      "date": "2025-12-02",
      "balance": 42933.02,
      "profit": -150,
      "description": "Warriors +11.5",
      "result": "loss"
    },
    {
      "date": "2025-12-03",
      "balance": 43063.45,
      "profit": 130.43,
      "description": "Spurs +8.5",
      "result": "win"
    },
    {
      "date": "2025-12-03",
      "balance": 43106.93,
      "profit": 43.48,
      "description": "Stars/Devils Under 6",
      "result": "win"
    },
    {
      "date": "2025-12-03",
      "balance": 43292.12,
      "profit": 185.19,
      "description": "Trail Blazers +11.5",
      "result": "win"
    },
    {
      "date": "2025-12-03",
      "balance": 43428.48,
      "profit": 136.36,
      "description": "Towson -6.5",
      "result": "win"
    },
    {
      "date": "2025-12-03",
      "balance": 43540.09,
      "profit": 111.61,
      "description": "Detroit -3.5",
      "result": "win"
    },
    {
      "date": "2025-12-03",
      "balance": 43440.09,
      "profit": -100,
      "description": "Cleveland St +12.5",
      "result": "loss"
    },
    {
      "date": "2025-12-03",
      "balance": 43340.09,
      "profit": -100,
      "description": "Sabres/Flyers Under 6",
      "result": "loss"
    },
    {
      "date": "2025-12-03",
      "balance": 43386.39,
      "profit": 46.3,
      "description": "Bucks +4.5",
      "result": "win"
    },
    {
      "date": "2025-12-03",
      "balance": 43236.39,
      "profit": -150,
      "description": "Kings +15.5",
      "result": "loss"
    },
    {
      "date": "2025-12-03",
      "balance": 43379.25,
      "profit": 142.86,
      "description": "Mavericks +4.5",
      "result": "win"
    },
    {
      "date": "2025-12-03",
      "balance": 43279.25,
      "profit": -100,
      "description": "Northwestern +10.5",
      "result": "loss"
    },
    {
      "date": "2025-12-04",
      "balance": 43559.25,
      "profit": 280,
      "description": "Penguins ML",
      "result": "win"
    },
    {
      "date": "2025-12-04",
      "balance": 43724.25,
      "profit": 165,
      "description": "Rangers ML",
      "result": "win"
    },
    {
      "date": "2025-12-04",
      "balance": 43907.25,
      "profit": 183,
      "description": "Bruins ML",
      "result": "win"
    },
    {
      "date": "2025-12-04",
      "balance": 44107.25,
      "profit": 200,
      "description": "S. Florida -1.5",
      "result": "win"
    },
    {
      "date": "2025-12-04",
      "balance": 43957.25,
      "profit": -150,
      "description": "Nets +5.5",
      "result": "loss"
    },
    {
      "date": "2025-12-04",
      "balance": 44063.25,
      "profit": 106,
      "description": "Flames ML",
      "result": "win"
    },
    {
      "date": "2025-12-04",
      "balance": 43913.25,
      "profit": -150,
      "description": "UCSB -13.5",
      "result": "loss"
    },
    {
      "date": "2025-12-05",
      "balance": 44153.25,
      "profit": 240,
      "description": "Jets -1.5",
      "result": "win"
    },
    {
      "date": "2025-12-05",
      "balance": 44240.21,
      "profit": 86.96,
      "description": "Heat +6.5",
      "result": "win"
    },
    {
      "date": "2025-12-05",
      "balance": 44090.21,
      "profit": -150,
      "description": "Lakers +8.5",
      "result": "loss"
    },
    {
      "date": "2025-12-05",
      "balance": 43990.21,
      "profit": -100,
      "description": "Kentucky +5.5",
      "result": "loss"
    },
    {
      "date": "2025-12-05",
      "balance": 44107.03,
      "profit": 116.82,
      "description": "Troy +24.5",
      "result": "win"
    },
    {
      "date": "2025-12-05",
      "balance": 43907.03,
      "profit": -200,
      "description": "Jazz +15.5",
      "result": "loss"
    },
    {
      "date": "2025-12-05",
      "balance": 44016.68,
      "profit": 109.65,
      "description": "Hornets +7.5",
      "result": "win"
    },
    {
      "date": "2025-12-05",
      "balance": 43941.68,
      "profit": -75,
      "description": "Canucks +1.5",
      "result": "loss"
    },
    {
      "date": "2025-12-05",
      "balance": 43791.68,
      "profit": -150,
      "description": "Mavericks +15.5",
      "result": "loss"
    },
    {
      "date": "2025-12-06",
      "balance": 43641.68,
      "profit": -150,
      "description": "Rhode Island +7.5",
      "result": "loss"
    },
    {
      "date": "2025-12-06",
      "balance": 43491.68,
      "profit": -150,
      "description": "Michigan St +1",
      "result": "loss"
    },
    {
      "date": "2025-12-06",
      "balance": 43291.68,
      "profit": -200,
      "description": "Alabama +2.5",
      "result": "loss"
    },
    {
      "date": "2025-12-06",
      "balance": 43141.68,
      "profit": -150,
      "description": "Avalanche -1.5",
      "result": "loss"
    },
    {
      "date": "2025-12-06",
      "balance": 43278.04,
      "profit": 136.36,
      "description": "Kings +8.5",
      "result": "win"
    },
    {
      "date": "2025-12-06",
      "balance": 43420.9,
      "profit": 142.86,
      "description": "Indiana +5.5",
      "result": "win"
    },
    {
      "date": "2025-12-06",
      "balance": 43551.33,
      "profit": 130.43,
      "description": "Duke +4.5",
      "result": "win"
    },
    {
      "date": "2025-12-07",
      "balance": 43733.15,
      "profit": 181.82,
      "description": "Vikings +1.5",
      "result": "win"
    },
    {
      "date": "2025-12-07",
      "balance": 43824.06,
      "profit": 90.91,
      "description": "Raiders +8.5",
      "result": "win"
    },
    {
      "date": "2025-12-07",
      "balance": 43724.06,
      "profit": -100,
      "description": "Bears +6.5",
      "result": "loss"
    },
    {
      "date": "2025-12-07",
      "balance": 43624.06,
      "profit": -100,
      "description": "Cardinals +9.5",
      "result": "loss"
    },
    {
      "date": "2025-12-07",
      "balance": 43771.12,
      "profit": 147.06,
      "description": "Northeastern -1.5",
      "result": "win"
    },
    {
      "date": "2025-12-07",
      "balance": 43521.12,
      "profit": -250,
      "description": "LSU +5.5",
      "result": "loss"
    },
    {
      "date": "2025-12-07",
      "balance": 43662.63,
      "profit": 141.51,
      "description": "UNLV +9.5",
      "result": "win"
    },
    {
      "date": "2025-12-07",
      "balance": 43708.08,
      "profit": 45.45,
      "description": "SMU +2",
      "result": "win"
    },
    {
      "date": "2025-12-07",
      "balance": 43658.08,
      "profit": -50,
      "description": "Creighton +5.5",
      "result": "loss"
    },
    {
      "date": "2025-12-08",
      "balance": 43848.56,
      "profit": 190.48,
      "description": "Kings ML",
      "result": "win"
    },
    {
      "date": "2025-12-08",
      "balance": 44048.56,
      "profit": 200,
      "description": "Chargers +2.5",
      "result": "win"
    },
    {
      "date": "2025-12-08",
      "balance": 44182.49,
      "profit": 133.93,
      "description": "Pelicans +9.5",
      "result": "win"
    },
    {
      "date": "2025-12-08",
      "balance": 44277.73,
      "profit": 95.24,
      "description": "Grambling St +8.5",
      "result": "win"
    },
    {
      "date": "2025-12-08",
      "balance": 44372.97,
      "profit": 95.24,
      "description": "Grambling St +8.5",
      "result": "win"
    },
    {
      "date": "2025-12-08",
      "balance": 44272.97,
      "profit": -100,
      "description": "Sabres ML",
      "result": "loss"
    },
    {
      "date": "2025-12-08",
      "balance": 44384.91,
      "profit": 111.94,
      "description": "Wild ML",
      "result": "win"
    },
    {
      "date": "2025-12-08",
      "balance": 44480.15,
      "profit": 95.24,
      "description": "Eagles/Chargers Under 41.5",
      "result": "win"
    },
    {
      "date": "2025-12-09",
      "balance": 44380.15,
      "profit": -100,
      "description": "Heat ML",
      "result": "loss"
    },
    {
      "date": "2025-12-09",
      "balance": 44470.15,
      "profit": 90,
      "description": "Hurricanes -1.5",
      "result": "win"
    },
    {
      "date": "2025-12-09",
      "balance": 44563.61,
      "profit": 93.46,
      "description": "Illinois -3",
      "result": "win"
    },
    {
      "date": "2025-12-09",
      "balance": 44701.11,
      "profit": 137.5,
      "description": "Bruins ML",
      "result": "win"
    },
    {
      "date": "2025-12-09",
      "balance": 44841.96,
      "profit": 140.85,
      "description": "Stars ML",
      "result": "win"
    },
    {
      "date": "2025-12-09",
      "balance": 44929.99,
      "profit": 88.03,
      "description": "Stars ML",
      "result": "win"
    },
    {
      "date": "2025-12-09",
      "balance": 45020.9,
      "profit": 90.91,
      "description": "UConn -3.5",
      "result": "win"
    },
    {
      "date": "2025-12-09",
      "balance": 44920.9,
      "profit": -100,
      "description": "LBSU/SJSU Under 141",
      "result": "loss"
    },
    {
      "date": "2025-12-10",
      "balance": 44770.9,
      "profit": -150,
      "description": "Delaware @ George Washington Over 152.5",
      "result": "loss"
    },
    {
      "date": "2025-12-10",
      "balance": 44862.64,
      "profit": 91.74,
      "description": "UMass +1.5",
      "result": "win"
    },
    {
      "date": "2025-12-10",
      "balance": 45005.5,
      "profit": 142.86,
      "description": "Colgate +9.5",
      "result": "win"
    },
    {
      "date": "2025-12-10",
      "balance": 44905.5,
      "profit": -100,
      "description": "Liberty @ NC State Over 151.5",
      "result": "loss"
    },
    {
      "date": "2025-12-10",
      "balance": 44805.5,
      "profit": -100,
      "description": "Liberty +12.5",
      "result": "loss"
    },
    {
      "date": "2025-12-10",
      "balance": 44941.86,
      "profit": 136.36,
      "description": "Minnesota @ Purdue Under 143",
      "result": "win"
    },
    {
      "date": "2025-12-10",
      "balance": 44816.86,
      "profit": -125,
      "description": "Eastern Illinois +5.5",
      "result": "loss"
    },
    {
      "date": "2025-12-10",
      "balance": 44716.86,
      "profit": -100,
      "description": "LA Kings -1.5",
      "result": "loss"
    },
    {
      "date": "2025-12-10",
      "balance": 44812.1,
      "profit": 95.24,
      "description": "Spurs +7.5",
      "result": "win"
    },
    {
      "date": "2025-12-11",
      "balance": 44612.1,
      "profit": -200,
      "description": "Kings +10.5",
      "result": "loss"
    },
    {
      "date": "2025-12-11",
      "balance": 44748.1,
      "profit": 136,
      "description": "Bucks +9.5",
      "result": "win"
    },
    {
      "date": "2025-12-11",
      "balance": 44891.1,
      "profit": 143,
      "description": "Clippers +9.5",
      "result": "win"
    },
    {
      "date": "2025-12-11",
      "balance": 45005.1,
      "profit": 114,
      "description": "Iowa +12.5",
      "result": "win"
    },
    {
      "date": "2025-12-11",
      "balance": 44880.1,
      "profit": -125,
      "description": "Iowa/Iowa St O140.5",
      "result": "loss"
    },
    {
      "date": "2025-12-11",
      "balance": 45225.1,
      "profit": 345,
      "description": "Falcons ML",
      "result": "win"
    },
    {
      "date": "2025-12-11",
      "balance": 45312.1,
      "profit": 87,
      "description": "Sabres ML",
      "result": "win"
    },
    {
      "date": "2025-12-11",
      "balance": 45409.1,
      "profit": 97,
      "description": "Bruins ML",
      "result": "win"
    },
    {
      "date": "2025-12-11",
      "balance": 45453.1,
      "profit": 44,
      "description": "Avalanche ML",
      "result": "win"
    },
    {
      "date": "2025-12-12",
      "balance": 45253.1,
      "profit": -200,
      "description": "Nets +7.5",
      "result": "loss"
    },
    {
      "date": "2025-12-12",
      "balance": 45344.01,
      "profit": 90.91,
      "description": "Jazz +7.5",
      "result": "win"
    },
    {
      "date": "2025-12-12",
      "balance": 45486.87,
      "profit": 142.86,
      "description": "Austin Peay +3.5",
      "result": "win"
    },
    {
      "date": "2025-12-12",
      "balance": 45336.87,
      "profit": -150,
      "description": "Nets +7.5",
      "result": "loss"
    },
    {
      "date": "2025-12-12",
      "balance": 45136.87,
      "profit": -200,
      "description": "Blackhawks ML",
      "result": "loss"
    },
    {
      "date": "2025-12-12",
      "balance": 45247.49,
      "profit": 110.62,
      "description": "Blackhawks/Blues Under 6",
      "result": "win"
    },
    {
      "date": "2025-12-12",
      "balance": 45342.73,
      "profit": 95.24,
      "description": "Austin Peay +3.5",
      "result": "win"
    },
    {
      "date": "2025-12-12",
      "balance": 45398.29,
      "profit": 55.56,
      "description": "Utah HC ML",
      "result": "win"
    },
    {
      "date": "2025-12-13",
      "balance": 45248.29,
      "profit": -150,
      "description": "Ducks ML",
      "result": "loss"
    },
    {
      "date": "2025-12-13",
      "balance": 45384.65,
      "profit": 136.36,
      "description": "George Washington +14.5",
      "result": "win"
    },
    {
      "date": "2025-12-13",
      "balance": 45521.01,
      "profit": 136.36,
      "description": "Army/Navy Under 38.5",
      "result": "win"
    },
    {
      "date": "2025-12-13",
      "balance": 45421.01,
      "profit": -100,
      "description": "Illinois -10.5",
      "result": "loss"
    },
    {
      "date": "2025-12-13",
      "balance": 45271.01,
      "profit": -150,
      "description": "NC State -2.5",
      "result": "loss"
    },
    {
      "date": "2025-12-13",
      "balance": 45196.01,
      "profit": -75,
      "description": "Magic +4.5",
      "result": "loss"
    },
    {
      "date": "2025-12-13",
      "balance": 45386.01,
      "profit": 190,
      "description": "Oilers -1.5",
      "result": "win"
    },
    {
      "date": "2025-12-13",
      "balance": 45261.01,
      "profit": -125,
      "description": "Hurricanes -1.5",
      "result": "loss"
    },
    {
      "date": "2025-12-13",
      "balance": 45061.01,
      "profit": -200,
      "description": "Canadiens ML",
      "result": "loss"
    },
    {
      "date": "2025-12-13",
      "balance": 44911.01,
      "profit": -150,
      "description": "Canadiens ML",
      "result": "loss"
    },
    {
      "date": "2025-12-13",
      "balance": 44811.01,
      "profit": -100,
      "description": "South Carolina -23",
      "result": "loss"
    },
    {
      "date": "2025-12-13",
      "balance": 44902.75,
      "profit": 91.74,
      "description": "Spurs/Thunder Under 232.5",
      "result": "win"
    },
    {
      "date": "2025-12-14",
      "balance": 45045.61,
      "profit": 142.86,
      "description": "Bills -2.5 vs Patriots",
      "result": "win"
    },
    {
      "date": "2025-12-14",
      "balance": 45136.52,
      "profit": 90.91,
      "description": "Ravens -2.5 vs Bengals",
      "result": "win"
    },
    {
      "date": "2025-12-14",
      "balance": 45196.52,
      "profit": 60,
      "description": "East Carolina +1.5 vs Buffalo",
      "result": "win"
    },
    {
      "date": "2025-12-14",
      "balance": 45096.52,
      "profit": -100,
      "description": "UAB -6.5 vs Troy",
      "result": "loss"
    },
    {
      "date": "2025-12-14",
      "balance": 45187.43,
      "profit": 90.91,
      "description": "Wizards +10 vs Pacers",
      "result": "win"
    },
    {
      "date": "2025-12-14",
      "balance": 45323.79,
      "profit": 136.36,
      "description": "Saints +1.5 vs Panthers",
      "result": "win"
    },
    {
      "date": "2025-12-14",
      "balance": 45392.6,
      "profit": 68.81,
      "description": "Chicago State +13.5 vs Loyola Illinois",
      "result": "win"
    },
    {
      "date": "2025-12-14",
      "balance": 45292.6,
      "profit": -100,
      "description": "Bruins ML vs Wild",
      "result": "loss"
    },
    {
      "date": "2025-12-14",
      "balance": 45338.05,
      "profit": 45.45,
      "description": "Boise State +2.5 vs Saint Mary's",
      "result": "win"
    },
    {
      "date": "2025-12-14",
      "balance": 45436.09,
      "profit": 98.04,
      "description": "Nets +1.5 vs Bucks",
      "result": "win"
    },
    {
      "date": "2025-12-15",
      "balance": 45536.09,
      "profit": 100,
      "description": "Ducks ML",
      "result": "win"
    },
    {
      "date": "2025-12-15",
      "balance": 45641.09,
      "profit": 105,
      "description": "Panthers ML",
      "result": "win"
    },
    {
      "date": "2025-12-15",
      "balance": 45566.09,
      "profit": -75,
      "description": "Gardner-Webb +10.5",
      "result": "loss"
    },
    {
      "date": "2025-12-15",
      "balance": 45657.83,
      "profit": 91.74,
      "description": "Raptors +6",
      "result": "win"
    },
    {
      "date": "2025-12-15",
      "balance": 45753.07,
      "profit": 95.24,
      "description": "Predators ML",
      "result": "win"
    },
    {
      "date": "2025-12-15",
      "balance": 45603.07,
      "profit": -150,
      "description": "Dolphins/Steelers Under 42.5",
      "result": "loss"
    },
    {
      "date": "2025-12-15",
      "balance": 45693.98,
      "profit": 90.91,
      "description": "Grizzlies +4.5",
      "result": "win"
    },
    {
      "date": "2025-12-16",
      "balance": 45824.41,
      "profit": 130.43478260869566,
      "description": "Jacksonville State -2.5",
      "result": "win"
    },
    {
      "date": "2025-12-16",
      "balance": 46040.41,
      "profit": 216,
      "description": "Flyers ML",
      "result": "win"
    },
    {
      "date": "2025-12-16",
      "balance": 45915.41,
      "profit": -125,
      "description": "Blackhawks ML",
      "result": "loss"
    },
    {
      "date": "2025-12-16",
      "balance": 45815.41,
      "profit": -100,
      "description": "Islanders ML",
      "result": "loss"
    },
    {
      "date": "2025-12-16",
      "balance": 45715.41,
      "profit": -100,
      "description": "Ducks ML",
      "result": "loss"
    },
    {
      "date": "2025-12-16",
      "balance": 45858.27,
      "profit": 142.85714285714283,
      "description": "Lipscomb +31.5",
      "result": "win"
    },
    {
      "date": "2025-12-17",
      "balance": 45758.27,
      "profit": -100,
      "description": "Jets ML",
      "result": "loss"
    },
    {
      "date": "2025-12-17",
      "balance": 45708.27,
      "profit": -50,
      "description": "Jets ML",
      "result": "loss"
    },
    {
      "date": "2025-12-17",
      "balance": 45890.27,
      "profit": 182,
      "description": "Grizzlies +8.5",
      "result": "win"
    },
    {
      "date": "2025-12-17",
      "balance": 46026.27,
      "profit": 136,
      "description": "Bulls +5.5",
      "result": "win"
    },
    {
      "date": "2025-12-17",
      "balance": 46117.27,
      "profit": 91,
      "description": "Bulls +5.5",
      "result": "win"
    },
    {
      "date": "2025-12-17",
      "balance": 46160.27,
      "profit": 43,
      "description": "Delaware +1",
      "result": "win"
    },
    {
      "date": "2025-12-18",
      "balance": 46226.94,
      "profit": 66.67,
      "description": "Capitals ML",
      "result": "win"
    },
    {
      "date": "2025-12-18",
      "balance": 46317.85,
      "profit": 90.91,
      "description": "Thunder -17",
      "result": "win"
    },
    {
      "date": "2025-12-18",
      "balance": 46167.85,
      "profit": -150,
      "description": "Under 42.5",
      "result": "loss"
    },
    {
      "date": "2025-12-18",
      "balance": 46067.85,
      "profit": -100,
      "description": "Pistons -7",
      "result": "loss"
    },
    {
      "date": "2025-12-18",
      "balance": 45967.85,
      "profit": -100,
      "description": "Lakers -9.5",
      "result": "loss"
    },
    {
      "date": "2025-12-18",
      "balance": 45917.85,
      "profit": -50,
      "description": "Magic +7",
      "result": "loss"
    },
    {
      "date": "2025-12-18",
      "balance": 45817.85,
      "profit": -100,
      "description": "Missouri St +1.5",
      "result": "loss"
    },
    {
      "date": "2025-12-18",
      "balance": 45717.85,
      "profit": -100,
      "description": "Missouri St ML",
      "result": "loss"
    },
    {
      "date": "2025-12-19",
      "balance": 45808.76,
      "profit": 90.91,
      "description": "Seton Hall +1",
      "result": "win"
    },
    {
      "date": "2025-12-19",
      "balance": 45608.76,
      "profit": -200,
      "description": "Heat +7",
      "result": "loss"
    },
    {
      "date": "2025-12-19",
      "balance": 45696.48,
      "profit": 87.72,
      "description": "76ers +6.5",
      "result": "win"
    },
    {
      "date": "2025-12-19",
      "balance": 45496.48,
      "profit": -200,
      "description": "FAMU/Tarleton Over 145.5",
      "result": "loss"
    },
    {
      "date": "2025-12-19",
      "balance": 45587.39,
      "profit": 90.91,
      "description": "Belmont/UCI Under 151.5",
      "result": "win"
    },
    {
      "date": "2025-12-19",
      "balance": 45678.3,
      "profit": 90.91,
      "description": "Timberwolves +7.5",
      "result": "win"
    },
    {
      "date": "2025-12-19",
      "balance": 45478.3,
      "profit": -200,
      "description": "N. Alabama/LMU Under 140.5",
      "result": "loss"
    },
    {
      "date": "2025-12-19",
      "balance": 45378.3,
      "profit": -100,
      "description": "North Alabama +9.5",
      "result": "loss"
    },
    {
      "date": "2025-12-19",
      "balance": 45469.21,
      "profit": 90.91,
      "description": "Seattle +7.5",
      "result": "win"
    },
    {
      "date": "2025-12-20",
      "balance": 45369.21,
      "profit": -100,
      "description": "Miami/Texas A&M Over 48.5",
      "result": "loss"
    },
    {
      "date": "2025-12-20",
      "balance": 45269.21,
      "profit": -100,
      "description": "Texas A&M -2.5",
      "result": "loss"
    },
    {
      "date": "2025-12-20",
      "balance": 45365.21,
      "profit": 96,
      "description": "Wild -1.5",
      "result": "win"
    },
    {
      "date": "2025-12-20",
      "balance": 45420.21,
      "profit": 55,
      "description": "Senators -1.5",
      "result": "win"
    },
    {
      "date": "2025-12-20",
      "balance": 45320.21,
      "profit": -100,
      "description": "Commanders +7.5",
      "result": "loss"
    },
    {
      "date": "2025-12-20",
      "balance": 45170.21,
      "profit": -150,
      "description": "Commanders +7.5",
      "result": "loss"
    },
    {
      "date": "2025-12-20",
      "balance": 45300.64,
      "profit": 130.43,
      "description": "76ers -2.5",
      "result": "win"
    },
    {
      "date": "2025-12-20",
      "balance": 45389.93,
      "profit": 89.29,
      "description": "Pelicans -2",
      "result": "win"
    },
    {
      "date": "2025-12-20",
      "balance": 45339.93,
      "profit": -50,
      "description": "Packers +1.5",
      "result": "loss"
    },
    {
      "date": "2025-12-20",
      "balance": 45239.93,
      "profit": -100,
      "description": "Packers +1.5",
      "result": "loss"
    },
    {
      "date": "2025-12-20",
      "balance": 45335.17,
      "profit": 95.24,
      "description": "Suns +6",
      "result": "win"
    },
    {
      "date": "2025-12-20",
      "balance": 45426.91,
      "profit": 91.74,
      "description": "Clippers +1.5",
      "result": "win"
    },
    {
      "date": "2025-12-20",
      "balance": 45517.82,
      "profit": 90.91,
      "description": "Clippers +1.5",
      "result": "win"
    },
    {
      "date": "2025-12-21",
      "balance": 45467.82,
      "profit": -50,
      "description": "Giants +2.5",
      "result": "loss"
    },
    {
      "date": "2025-12-21",
      "balance": 45558.73,
      "profit": 90.91,
      "description": "Panthers +3.5",
      "result": "win"
    },
    {
      "date": "2025-12-21",
      "balance": 45672.37,
      "profit": 113.64,
      "description": "Browns +10.5",
      "result": "win"
    },
    {
      "date": "2025-12-21",
      "balance": 45763.28,
      "profit": 90.91,
      "description": "Jaguars +5.5",
      "result": "win"
    },
    {
      "date": "2025-12-21",
      "balance": 45663.28,
      "profit": -100,
      "description": "Wild ML",
      "result": "loss"
    },
    {
      "date": "2025-12-21",
      "balance": 45728.5,
      "profit": 65.22,
      "description": "Heat +8",
      "result": "win"
    },
    {
      "date": "2025-12-21",
      "balance": 45578.5,
      "profit": -150,
      "description": "Canadiens ML",
      "result": "loss"
    },
    {
      "date": "2025-12-21",
      "balance": 45478.5,
      "profit": -100,
      "description": "Canadiens ML",
      "result": "loss"
    },
    {
      "date": "2025-12-21",
      "balance": 45660.32,
      "profit": 181.82,
      "description": "Bucks +12.5",
      "result": "win"
    },
    {
      "date": "2025-12-21",
      "balance": 45803.18,
      "profit": 142.86,
      "description": "Wizards +15.5",
      "result": "win"
    },
    {
      "date": "2025-12-22",
      "balance": 45703.18,
      "profit": -100,
      "description": "Blues ML",
      "result": "loss"
    },
    {
      "date": "2025-12-22",
      "balance": 45880.17,
      "profit": 176.99,
      "description": "Hornets +9.5",
      "result": "win"
    },
    {
      "date": "2025-12-22",
      "balance": 45975.41,
      "profit": 95.24,
      "description": "Pelicans -1",
      "result": "win"
    },
    {
      "date": "2025-12-22",
      "balance": 46023.03,
      "profit": 47.62,
      "description": "Pelicans -1",
      "result": "win"
    },
    {
      "date": "2025-12-22",
      "balance": 45923.03,
      "profit": -100,
      "description": "Davidson +16.5",
      "result": "loss"
    },
    {
      "date": "2025-12-22",
      "balance": 45823.03,
      "profit": -100,
      "description": "Colts +5.5",
      "result": "loss"
    },
    {
      "date": "2025-12-22",
      "balance": 45623.03,
      "profit": -200,
      "description": "Jazz +13.5",
      "result": "loss"
    },
    {
      "date": "2025-12-23",
      "balance": 45712.32,
      "profit": 89.29,
      "description": "WKU +2.5",
      "result": "win"
    },
    {
      "date": "2025-12-23",
      "balance": 45562.32,
      "profit": -150,
      "description": "Devils ML",
      "result": "loss"
    },
    {
      "date": "2025-12-23",
      "balance": 45657.56,
      "profit": 95.24,
      "description": "Raptors +5.5",
      "result": "win"
    },
    {
      "date": "2025-12-23",
      "balance": 45507.56,
      "profit": -150,
      "description": "Pelicans +8.5",
      "result": "loss"
    },
    {
      "date": "2025-12-23",
      "balance": 45602.8,
      "profit": 95.24,
      "description": "Ohio +6.5",
      "result": "win"
    },
    {
      "date": "2025-12-23",
      "balance": 45502.8,
      "profit": -100,
      "description": "Sharks ML",
      "result": "loss"
    },
    {
      "date": "2025-12-24",
      "balance": 45502.8,
      "profit": 0,
      "description": "No Picks - Christmas Eve",
      "result": "no_action"
    },
    {
      "date": "2025-12-25",
      "balance": 45684.62,
      "profit": 181.82,
      "description": "Spurs +10",
      "result": "win"
    },
    {
      "date": "2025-12-25",
      "balance": 46004.62,
      "profit": 320,
      "description": "Spurs ML",
      "result": "win"
    },
    {
      "date": "2025-12-25",
      "balance": 46118.26,
      "profit": 113.64,
      "description": "Vikings +7.5",
      "result": "win"
    },
    {
      "date": "2025-12-25",
      "balance": 46213.5,
      "profit": 95.24,
      "description": "Lions/Vikings U43.5",
      "result": "win"
    },
    {
      "date": "2025-12-25",
      "balance": 46088.5,
      "profit": -125,
      "description": "Mavericks +8.5",
      "result": "loss"
    },
    {
      "date": "2025-12-25",
      "balance": 46013.5,
      "profit": -75,
      "description": "Mavericks ML",
      "result": "loss"
    },
    {
      "date": "2025-12-25",
      "balance": 46108.74,
      "profit": 95.24,
      "description": "Chiefs +13.5",
      "result": "win"
    },
    {
      "date": "2025-12-26",
      "balance": 46008.74,
      "profit": -100,
      "description": "C. Michigan +12.5",
      "result": "loss"
    },
    {
      "date": "2025-12-26",
      "balance": 45808.74,
      "profit": -200,
      "description": "New Mexico +1.5",
      "result": "loss"
    },
    {
      "date": "2025-12-26",
      "balance": 45852.6,
      "profit": 43.86,
      "description": "Wizards +7.5",
      "result": "win"
    },
    {
      "date": "2025-12-26",
      "balance": 45752.6,
      "profit": -100,
      "description": "Bucks +5.5",
      "result": "loss"
    },
    {
      "date": "2025-12-26",
      "balance": 45702.6,
      "profit": -50,
      "description": "Bucks +5.5",
      "result": "loss"
    },
    {
      "date": "2025-12-26",
      "balance": 45793.51,
      "profit": 90.91,
      "description": "FIU/UTSA Over 60.5",
      "result": "win"
    },
    {
      "date": "2025-12-27",
      "balance": null,
      "description": "Texans +1.5",
      "result": "win"
    },
    {
      "date": "2025-12-27",
      "balance": null,
      "description": "Rangers ML",
      "result": "loss"
    },
    {
      "date": "2025-12-27",
      "balance": null,
      "description": "Wild ML",
      "result": "win"
    },
    {
      "date": "2025-12-27",
      "balance": null,
      "description": "Bruins ML",
      "result": "loss"
    },
    {
      "date": "2025-12-27",
      "balance": null,
      "description": "Senators ML",
      "result": "loss"
    },
    {
      "date": "2025-12-27",
      "balance": null,
      "description": "Ravens/Packers Under 38.5",
      "result": "loss"
    },
    {
      "date": "2025-12-27",
      "balance": null,
      "description": "Predators ML",
      "result": "loss"
    },
    {
      "date": "2025-12-27",
      "balance": null,
      "description": "Jazz +16.5",
      "result": "win"
    },
    {
      "date": "2025-12-27",
      "balance": null,
      "description": "Jazz/Spurs Over 243.5",
      "result": "loss"
    },
    {
      "date": "2025-12-27",
      "balance": null,
      "description": "Nets +11",
      "result": "win"
    },
    {
      "date": "2025-12-27",
      "balance": null,
      "description": "Ducks ML",
      "result": "loss"
    },
    {
      "date": "2025-12-27",
      "balance": null,
      "description": "Ducks/Kings Under 6.5",
      "result": "loss"
    }
  ],
  "lastUpdated": "2025-12-28T12:21:59.703626Z",
  "convictionPerformance": {
    "80+": {
      "wins": 23,
      "losses": 14,
      "pnl": 1573.85,
      "roi": 26.01,
      "winRate": 62.16,
      "bets": 37
    },
    "70-79": {
      "wins": 27,
      "losses": 21,
      "pnl": 739.57,
      "roi": 11.16,
      "winRate": 56.25,
      "bets": 48
    },
    "60-69": {
      "wins": 40,
      "losses": 22,
      "pnl": 1532.65,
      "roi": 21.74,
      "winRate": 64.52,
      "bets": 62
    },
    "50-59": {
      "wins": 34,
      "losses": 29,
      "pnl": 797.15,
      "roi": 13.34,
      "winRate": 53.97,
      "bets": 64
    },
    "40-49": {
      "wins": 8,
      "losses": 5,
      "pnl": 117.28,
      "roi": 12.35,
      "winRate": 61.54,
      "bets": 13
    }
  }
}