{
  "asOfDate": "2025-12-03",
  "combined": {
    "balance": 42925.38,
    "startingBalance": 40000,
    "netPL": 2925.38,
    "roi": 7.31,
    "record": {
      "wins": 101,
      "losses": 72,
      "pushes": 2
    },
    "winRate": 58.38,
    "unitsWon": 29.25,
    "sharpe": null
  },
  "funds": {
    "VectorFund": {
      "name": "Flagship Vector Fund",
      "tagline": "Model-driven edge detection",
      "balance": 10510.42,
      "startingBalance": 10000,
      "netPL": 510.42,
      "roi": 5.1,
      "record": {
        "wins": 67,
        "losses": 58,
        "pushes": 1
      },
      "winRate": 53.6,
      "unitsWon": 5.1,
      "color": "#1a1a1a",
      "status": "active"
    },
    "SharpFund": {
      "name": "Sharp Fund",
      "tagline": "Following the smart money",
      "balance": 10888,
      "startingBalance": 10000,
      "netPL": 888,
      "roi": 8.88,
      "record": {
        "wins": 17,
        "losses": 8,
        "pushes": 0
      },
      "winRate": 68,
      "unitsWon": 8.88,
      "color": "#22c55e",
      "status": "active"
    },
    "ContraFund": {
      "name": "Contra Fund",
      "tagline": "Fading the public",
      "balance": 10735.89,
      "startingBalance": 10000,
      "netPL": 735.89,
      "roi": 7.36,
      "record": {
        "wins": 9,
        "losses": 2,
        "pushes": 0
      },
      "winRate": 81.82,
      "unitsWon": 7.36,
      "color": "#f97316",
      "status": "active"
    },
    "CatalystFund": {
      "name": "Catalyst Fund",
      "tagline": "Situational opportunities",
      "balance": 10791.07,
      "startingBalance": 10000,
      "netPL": 791.07,
      "roi": 7.91,
      "record": {
        "wins": 8,
        "losses": 4,
        "pushes": 1
      },
      "winRate": 66.67,
      "unitsWon": 7.91,
      "color": "#8b5cf6",
      "status": "active"
    }
  }
}